admin_gitlog/__init__.py
admin_gitlog/admin.py
admin_gitlog/apps.py
admin_gitlog/models.py
admin_gitlog/templates/admin/gitlog_custom_index.html
admin_gitlog/templatetags/__init__.py
admin_gitlog/templatetags/admin_gitlog_extras.py
django_admin_gitlog-0.2.dist-info/DESCRIPTION.rst
django_admin_gitlog-0.2.dist-info/METADATA
django_admin_gitlog-0.2.dist-info/RECORD
django_admin_gitlog-0.2.dist-info/WHEEL
django_admin_gitlog-0.2.dist-info/metadata.json
django_admin_gitlog-0.2.dist-info/top_level.txt
