Metadata-Version: 2.0
Name: django-admin-gitlog
Version: 0.2
Summary: Display a `git log` in your admin
Home-page: http://github.com/mdamien/django-admin-gitlog
Author: Damien MARIÉ
Author-email: damien@dam.io
License: MIT
Platform: UNKNOWN
Classifier: Environment :: Web Environment
Classifier: Framework :: Django
Classifier: Topic :: Internet :: WWW/HTTP
Classifier: Topic :: Internet :: WWW/HTTP :: Dynamic Content
Classifier: Development Status :: 2 - Pre-Alpha
Classifier: Intended Audience :: Developers
Classifier: Natural Language :: English
Classifier: License :: OSI Approved :: MIT License
Classifier: Programming Language :: Python :: 3
